{
  "appid": 1906860,
  "name": "Path to Ruin",
  "developer": "Brainwave 23 Studios",
  "publisher": "Brainwave 23 Studios",
  "tags": {
    "Early Access": 278,
    "RPG": 252,
    "Turn-Based Strategy": 226,
    "JRPG": 222,
    "Party-Based RPG": 217,
    "Exploration": 211,
    "Pixel Graphics": 201,
    "2D": 194,
    "Colorful": 186,
    "Atmospheric": 177,
    "Dark Humor": 168,
    "Emotional": 158,
    "Fantasy": 146,
    "Funny": 144,
    "Magic": 130,
    "Retro": 115,
    "Sci-fi": 99,
    "Combat": 82,
    "Controller": 64,
    "Story Rich": 45
  },
  "type": "game",
  "categories": [
    "Single-player",
    "Full controller support"
  ],
  "owners": "0 .. 20,000",
  "positive": 6,
  "negative": 0,
  "price": "499",
  "initialprice": "499",
  "discount": "0",
  "ccu": 0,
  "languages": "English",
  "platforms": {
    "windows": true,
    "mac": false,
    "linux": false
  },
  "release_date": "2022/10/7",
  "required_age": 0,
  "header_image": "https://cdn.akamai.steamstatic.com/steam/apps/1906860/header.jpg?t=1665134419",
  "genre": [
    "Adventure",
    "Indie",
    "RPG",
    "Early Access"
  ],
  "consensus_genre": "Early Access",
  "Meta Score": -1,
  "Like Histogram": [
    {
      "date": 1667268000,
      "recommendations_up": 1,
      "recommendations_down": 0
    }
  ],
  "Up 30 Days": 1,
  "Down 30 Days": 0,
  "Completion": [
    {
      "name": "NEW_ACHIEVEMENT_1_18",
      "percent": 7.599999904632568
    },
    {
      "name": "NEW_ACHIEVEMENT_1_17",
      "percent": 7.599999904632568
    },
    {
      "name": "NEW_ACHIEVEMENT_1_16",
      "percent": 7.599999904632568
    },
    {
      "name": "NEW_ACHIEVEMENT_1_15",
      "percent": 7.599999904632568
    },
    {
      "name": "NEW_ACHIEVEMENT_1_14",
      "percent": 7.599999904632568
    },
    {
      "name": "NEW_ACHIEVEMENT_1_13",
      "percent": 7.599999904632568
    },
    {
      "name": "NEW_ACHIEVEMENT_1_12",
      "percent": 7.599999904632568
    },
    {
      "name": "NEW_ACHIEVEMENT_1_11",
      "percent": 7.599999904632568
    },
    {
      "name": "NEW_ACHIEVEMENT_1_10",
      "percent": 7.599999904632568
    },
    {
      "name": "NEW_ACHIEVEMENT_1_9",
      "percent": 7.599999904632568
    },
    {
      "name": "NEW_ACHIEVEMENT_1_8",
      "percent": 7.599999904632568
    },
    {
      "name": "NEW_ACHIEVEMENT_1_7",
      "percent": 7.599999904632568
    },
    {
      "name": "NEW_ACHIEVEMENT_1_6",
      "percent": 7.599999904632568
    },
    {
      "name": "NEW_ACHIEVEMENT_1_5",
      "percent": 7.599999904632568
    },
    {
      "name": "NEW_ACHIEVEMENT_1_4",
      "percent": 7.599999904632568
    },
    {
      "name": "NEW_ACHIEVEMENT_1_3",
      "percent": 7.599999904632568
    },
    {
      "name": "NEW_ACHIEVEMENT_1_2",
      "percent": 7.599999904632568
    },
    {
      "name": "NEW_ACHIEVEMENT_1_1",
      "percent": 7.599999904632568
    },
    {
      "name": "NEW_ACHIEVEMENT_1_0",
      "percent": 7.599999904632568
    }
  ],
  "Rating": "?"
}