{
  "Average Playtime - 2 Weeks": 0,
  "Average Playtime - Forever": 614,
  "CCU Histogram": {
    "2022-12-08": 2337,
    "2022-12-09": 2171,
    "2022-12-10": 1901,
    "2022-12-11": 1701,
    "2022-12-12": 1501,
    "2022-12-13": 1302,
    "2022-12-14": 1299,
    "2022-12-15": 1296,
    "2022-12-16": 1219,
    "2022-12-17": 1143,
    "2022-12-18": 1067,
    "2022-12-19": 1026,
    "2022-12-20": 986,
    "2022-12-21": 946,
    "2022-12-22": 1056
  },
  "Completion": -1,
  "Down 30 Days": 57,
  "Like Histogram": [
    {
      "date": 1667268000,
      "recommendations_down": 3,
      "recommendations_up": 5
    },
    {
      "date": 1667354400,
      "recommendations_down": 1,
      "recommendations_up": 13
    },
    {
      "date": 1667440800,
      "recommendations_down": 2,
      "recommendations_up": 16
    },
    {
      "date": 1667527200,
      "recommendations_down": 1,
      "recommendations_up": 12
    },
    {
      "date": 1667613600,
      "recommendations_down": 1,
      "recommendations_up": 10
    },
    {
      "date": 1667700000,
      "recommendations_down": 2,
      "recommendations_up": 8
    },
    {
      "date": 1667786400,
      "recommendations_down": 1,
      "recommendations_up": 7
    },
    {
      "date": 1667872800,
      "recommendations_down": 3,
      "recommendations_up": 5
    },
    {
      "date": 1667959200,
      "recommendations_down": 1,
      "recommendations_up": 9
    },
    {
      "date": 1668045600,
      "recommendations_down": 2,
      "recommendations_up": 9
    },
    {
      "date": 1668132000,
      "recommendations_down": 3,
      "recommendations_up": 8
    },
    {
      "date": 1668218400,
      "recommendations_down": 0,
      "recommendations_up": 7
    },
    {
      "date": 1668304800,
      "recommendations_down": 1,
      "recommendations_up": 10
    },
    {
      "date": 1668391200,
      "recommendations_down": 1,
      "recommendations_up": 3
    },
    {
      "date": 1668477600,
      "recommendations_down": 2,
      "recommendations_up": 5
    },
    {
      "date": 1668564000,
      "recommendations_down": 1,
      "recommendations_up": 7
    },
    {
      "date": 1668650400,
      "recommendations_down": 0,
      "recommendations_up": 10
    },
    {
      "date": 1668736800,
      "recommendations_down": 0,
      "recommendations_up": 7
    },
    {
      "date": 1668823200,
      "recommendations_down": 2,
      "recommendations_up": 6
    },
    {
      "date": 1668909600,
      "recommendations_down": 3,
      "recommendations_up": 6
    },
    {
      "date": 1668996000,
      "recommendations_down": 3,
      "recommendations_up": 6
    },
    {
      "date": 1669082400,
      "recommendations_down": 2,
      "recommendations_up": 16
    },
    {
      "date": 1669168800,
      "recommendations_down": 4,
      "recommendations_up": 26
    },
    {
      "date": 1669255200,
      "recommendations_down": 3,
      "recommendations_up": 21
    },
    {
      "date": 1669341600,
      "recommendations_down": 3,
      "recommendations_up": 23
    },
    {
      "date": 1669428000,
      "recommendations_down": 2,
      "recommendations_up": 24
    },
    {
      "date": 1669514400,
      "recommendations_down": 4,
      "recommendations_up": 30
    },
    {
      "date": 1669600800,
      "recommendations_down": 2,
      "recommendations_up": 17
    },
    {
      "date": 1669687200,
      "recommendations_down": 4,
      "recommendations_up": 14
    },
    {
      "date": 1669773600,
      "recommendations_down": 0,
      "recommendations_up": 4
    }
  ],
  "Median Playtime - 2 Weeks": 0,
  "Median Playtime - Forever": 485,
  "Meta Score": -1,
  "Rating": "?",
  "Up 30 Days": 344,
  "User Score": -1,
  "appid": 1119730,
  "categories": [
    "Multi-player",
    "Single-player",
    "Co-op",
    "Steam Cloud",
    "Online PvP",
    "Online Co-op",
    "PvP"
  ],
  "ccu": 869,
  "consensus_genre": "Early Access",
  "developer": "Toxic Dog",
  "discount": "0",
  "genre": [
    "Simulation",
    "Early Access"
  ],
  "header_image": "https://cdn.akamai.steamstatic.com/steam/apps/1119730/header.jpg?t=1667475000",
  "initialprice": "2499",
  "languages": "English, French, Italian, German, Spanish - Spain, Portuguese - Brazil, Russian, Simplified Chinese, Traditional Chinese, Turkish, Korean, Polish",
  "name": "Ranch Simulator - Build, Farm, Hunt",
  "negative": 1591,
  "owners": "200,000 .. 500,000",
  "platforms": {
    "linux": false,
    "mac": false,
    "windows": true
  },
  "positive": 9080,
  "price": "2499",
  "publisher": "Excalibur Games",
  "release_date": "2021/03/4",
  "required_age": 0,
  "tags": {
    "Co-op": 278,
    "Driving": 183,
    "Early Access": 375,
    "Economy": 201,
    "Farming": 282,
    "Farming Sim": 303,
    "First-Person": 186,
    "Hunting": 251,
    "Immersive Sim": 197,
    "Indie": 199,
    "Management": 205,
    "Multiplayer": 324,
    "Nature": 199,
    "Online Co-Op": 316,
    "Open World": 302,
    "Realistic": 276,
    "Relaxing": 184,
    "Sandbox": 238,
    "Simulation": 340,
    "Singleplayer": 215
  },
  "type": "game"
}