{
  "appid": 1890590,
  "name": "SUPER NANARU",
  "developer": "TENTACLE SOFT",
  "publisher": "CFK Co., Ltd.",
  "tags": {
    "Action": 181,
    "Adventure": 174,
    "Casual": 170,
    "Action-Adventure": 144,
    "Arcade": 140,
    "Platformer": 130,
    "Precision Platformer": 124,
    "2D Platformer": 122,
    "Runner": 108,
    "2D": 97,
    "Side Scroller": 97,
    "Anime": 86,
    "Pixel Graphics": 81,
    "Comedy": 57,
    "Retro": 42,
    "Character Customization": 27,
    "Singleplayer": 27,
    "Indie": 22
  },
  "type": "game",
  "categories": [
    "Single-player",
    "Partial Controller Support"
  ],
  "owners": "0 .. 20,000",
  "positive": 23,
  "negative": 5,
  "price": "999",
  "initialprice": "999",
  "discount": "0",
  "ccu": 0,
  "languages": "English, Japanese, Korean, Russian",
  "platforms": {
    "windows": true,
    "mac": false,
    "linux": false
  },
  "release_date": "2022/03/23",
  "required_age": 0,
  "header_image": "https://cdn.akamai.steamstatic.com/steam/apps/1890590/header.jpg?t=1648081643",
  "genre": [
    "Action",
    "Adventure",
    "Casual",
    "Indie"
  ],
  "consensus_genre": "Action",
  "Meta Score": -1,
  "Like Histogram": [
    {
      "date": 1667268000,
      "recommendations_up": 0,
      "recommendations_down": 0
    },
    {
      "date": 1667354400,
      "recommendations_up": 0,
      "recommendations_down": 0
    },
    {
      "date": 1667440800,
      "recommendations_up": 0,
      "recommendations_down": 0
    },
    {
      "date": 1667527200,
      "recommendations_up": 0,
      "recommendations_down": 0
    },
    {
      "date": 1667613600,
      "recommendations_up": 0,
      "recommendations_down": 0
    },
    {
      "date": 1667700000,
      "recommendations_up": 0,
      "recommendations_down": 0
    },
    {
      "date": 1667786400,
      "recommendations_up": 0,
      "recommendations_down": 0
    },
    {
      "date": 1667872800,
      "recommendations_up": 0,
      "recommendations_down": 0
    },
    {
      "date": 1667959200,
      "recommendations_up": 0,
      "recommendations_down": 0
    },
    {
      "date": 1668045600,
      "recommendations_up": 0,
      "recommendations_down": 0
    },
    {
      "date": 1668132000,
      "recommendations_up": 0,
      "recommendations_down": 0
    },
    {
      "date": 1668218400,
      "recommendations_up": 0,
      "recommendations_down": 0
    },
    {
      "date": 1668304800,
      "recommendations_up": 0,
      "recommendations_down": 0
    },
    {
      "date": 1668391200,
      "recommendations_up": 0,
      "recommendations_down": 0
    },
    {
      "date": 1668477600,
      "recommendations_up": 0,
      "recommendations_down": 0
    },
    {
      "date": 1668564000,
      "recommendations_up": 0,
      "recommendations_down": 0
    },
    {
      "date": 1668650400,
      "recommendations_up": 0,
      "recommendations_down": 0
    },
    {
      "date": 1668736800,
      "recommendations_up": 0,
      "recommendations_down": 0
    },
    {
      "date": 1668823200,
      "recommendations_up": 0,
      "recommendations_down": 0
    },
    {
      "date": 1668909600,
      "recommendations_up": 0,
      "recommendations_down": 0
    },
    {
      "date": 1668996000,
      "recommendations_up": 0,
      "recommendations_down": 0
    },
    {
      "date": 1669082400,
      "recommendations_up": 0,
      "recommendations_down": 0
    },
    {
      "date": 1669168800,
      "recommendations_up": 0,
      "recommendations_down": 0
    },
    {
      "date": 1669255200,
      "recommendations_up": 0,
      "recommendations_down": 0
    },
    {
      "date": 1669341600,
      "recommendations_up": 0,
      "recommendations_down": 0
    },
    {
      "date": 1669428000,
      "recommendations_up": 0,
      "recommendations_down": 0
    },
    {
      "date": 1669514400,
      "recommendations_up": 0,
      "recommendations_down": 0
    },
    {
      "date": 1669600800,
      "recommendations_up": 0,
      "recommendations_down": 0
    },
    {
      "date": 1669687200,
      "recommendations_up": 0,
      "recommendations_down": 0
    },
    {
      "date": 1669773600,
      "recommendations_up": 0,
      "recommendations_down": 0
    }
  ],
  "Up 30 Days": 0,
  "Down 30 Days": 0,
  "Completion": 79.30000305175781,
  "Rating": "?"
}