{
  "appid": 1748210,
  "name": "Lovely Animal Stories",
  "developer": "Baltic Dog Games",
  "publisher": "Baltic Dog Games",
  "tags": {
    "Casual": 71,
    "Cute": 44,
    "Family Friendly": 41,
    "Puzzle": 38,
    "Point & Click": 34,
    "Colorful": 29,
    "Minimalist": 27,
    "2D": 26,
    "Walking Simulator": 22,
    "Comedy": 21,
    "Indie": 21,
    "Funny": 19,
    "Logic": 16,
    "Singleplayer": 15
  },
  "type": "game",
  "categories": [
    "Single-player"
  ],
  "owners": "0 .. 20,000",
  "positive": 1,
  "negative": 1,
  "price": "199",
  "initialprice": "199",
  "discount": "0",
  "ccu": 0,
  "languages": "English, French, German, Spanish - Spain, Russian",
  "platforms": {
    "windows": true,
    "mac": false,
    "linux": false
  },
  "release_date": "2021/09/26",
  "required_age": 0,
  "header_image": "https://cdn.akamai.steamstatic.com/steam/apps/1748210/header.jpg?t=1632748743",
  "genre": [
    "Casual",
    "Indie"
  ],
  "consensus_genre": "Casual",
  "Meta Score": -1,
  "Like Histogram": [
    {
      "date": 1667268000,
      "recommendations_up": 1,
      "recommendations_down": 0
    },
    {
      "date": 1667354400,
      "recommendations_up": 0,
      "recommendations_down": 0
    },
    {
      "date": 1667440800,
      "recommendations_up": 0,
      "recommendations_down": 1
    }
  ],
  "Up 30 Days": 1,
  "Down 30 Days": 1,
  "Completion": -1,
  "Rating": "?"
}