{
  "appid": 794850,
  "name": "Landflix Odyssey",
  "developer": "Fantastico Studio",
  "publisher": "Fantastico Studio",
  "tags": {
    "Action": 257,
    "Indie": 250,
    "Adventure": 248,
    "Parody ": 245,
    "Platformer": 241,
    "Side Scroller": 235,
    "1980s": 232,
    "Crowdfunded": 226,
    "Narration": 221,
    "Action-Adventure": 219,
    "Feature Film": 217,
    "Character Action Game": 215,
    "Pixel Graphics": 213,
    "Arcade": 204,
    "2D Platformer": 202,
    "Precision Platformer": 188,
    "Colorful": 175,
    "Comedy": 169,
    "Funny": 165,
    "Fantasy": 158
  },
  "type": "game",
  "categories": [
    "Multi-player",
    "Single-player",
    "Steam Achievements",
    "Steam Cloud",
    "Full controller support",
    "Remote Play Together"
  ],
  "owners": "0 .. 20,000",
  "positive": 11,
  "negative": 2,
  "price": "1499",
  "initialprice": "1499",
  "discount": "0",
  "ccu": 0,
  "languages": "English",
  "platforms": {
    "windows": true,
    "mac": true,
    "linux": false
  },
  "release_date": "2020/11/12",
  "required_age": 0,
  "header_image": "https://cdn.akamai.steamstatic.com/steam/apps/794850/header.jpg?t=1606826494",
  "genre": [
    "Action",
    "Adventure",
    "Indie"
  ],
  "consensus_genre": "Action",
  "Meta Score": -1,
  "Like Histogram": [
    {
      "date": 1667268000,
      "recommendations_up": 0,
      "recommendations_down": 1
    }
  ],
  "Up 30 Days": 0,
  "Down 30 Days": 1,
  "Completion": -1,
  "Rating": "?"
}