{
  "Average Playtime - 2 Weeks": 57,
  "Average Playtime - Forever": 43,
  "CCU Histogram": {
    "2022-12-08": 24,
    "2022-12-09": 21,
    "2022-12-10": 34,
    "2022-12-11": 35,
    "2022-12-12": 37,
    "2022-12-13": 39,
    "2022-12-14": 36,
    "2022-12-15": 34,
    "2022-12-16": 31,
    "2022-12-17": 28,
    "2022-12-18": 26,
    "2022-12-19": 22,
    "2022-12-20": 19,
    "2022-12-21": 16,
    "2022-12-22": 27
  },
  "Completion": 34.94999885559082,
  "Down 30 Days": 9,
  "Like Histogram": [
    {
      "date": 1667268000,
      "recommendations_down": 0,
      "recommendations_up": 6
    },
    {
      "date": 1667354400,
      "recommendations_down": 0,
      "recommendations_up": 8
    },
    {
      "date": 1667440800,
      "recommendations_down": 1,
      "recommendations_up": 1
    },
    {
      "date": 1667527200,
      "recommendations_down": 0,
      "recommendations_up": 1
    },
    {
      "date": 1667613600,
      "recommendations_down": 0,
      "recommendations_up": 2
    },
    {
      "date": 1667700000,
      "recommendations_down": 0,
      "recommendations_up": 4
    },
    {
      "date": 1667786400,
      "recommendations_down": 0,
      "recommendations_up": 4
    },
    {
      "date": 1667872800,
      "recommendations_down": 0,
      "recommendations_up": 7
    },
    {
      "date": 1667959200,
      "recommendations_down": 0,
      "recommendations_up": 7
    },
    {
      "date": 1668045600,
      "recommendations_down": 0,
      "recommendations_up": 1
    },
    {
      "date": 1668132000,
      "recommendations_down": 0,
      "recommendations_up": 1
    },
    {
      "date": 1668218400,
      "recommendations_down": 0,
      "recommendations_up": 2
    },
    {
      "date": 1668304800,
      "recommendations_down": 0,
      "recommendations_up": 5
    },
    {
      "date": 1668391200,
      "recommendations_down": 0,
      "recommendations_up": 4
    },
    {
      "date": 1668477600,
      "recommendations_down": 0,
      "recommendations_up": 1
    },
    {
      "date": 1668564000,
      "recommendations_down": 1,
      "recommendations_up": 1
    },
    {
      "date": 1668650400,
      "recommendations_down": 0,
      "recommendations_up": 0
    },
    {
      "date": 1668736800,
      "recommendations_down": 1,
      "recommendations_up": 1
    },
    {
      "date": 1668823200,
      "recommendations_down": 0,
      "recommendations_up": 2
    },
    {
      "date": 1668909600,
      "recommendations_down": 1,
      "recommendations_up": 4
    },
    {
      "date": 1668996000,
      "recommendations_down": 1,
      "recommendations_up": 4
    },
    {
      "date": 1669082400,
      "recommendations_down": 0,
      "recommendations_up": 9
    },
    {
      "date": 1669168800,
      "recommendations_down": 1,
      "recommendations_up": 7
    },
    {
      "date": 1669255200,
      "recommendations_down": 2,
      "recommendations_up": 6
    },
    {
      "date": 1669341600,
      "recommendations_down": 0,
      "recommendations_up": 1
    },
    {
      "date": 1669428000,
      "recommendations_down": 0,
      "recommendations_up": 4
    },
    {
      "date": 1669514400,
      "recommendations_down": 1,
      "recommendations_up": 1
    },
    {
      "date": 1669600800,
      "recommendations_down": 0,
      "recommendations_up": 3
    },
    {
      "date": 1669687200,
      "recommendations_down": 0,
      "recommendations_up": 3
    },
    {
      "date": 1669773600,
      "recommendations_down": 0,
      "recommendations_up": 0
    }
  ],
  "Median Playtime - 2 Weeks": 57,
  "Median Playtime - Forever": 54,
  "Meta Score": -1,
  "Rating": "?",
  "Up 30 Days": 100,
  "User Score": -1,
  "appid": 2005210,
  "categories": [
    "Single-player",
    "Steam Achievements",
    "Steam Cloud",
    "Full controller support"
  ],
  "ccu": 81,
  "consensus_genre": "Action",
  "developer": "8BitSkull",
  "discount": "0",
  "genre": [
    "Action"
  ],
  "header_image": "https://cdn.akamai.steamstatic.com/steam/apps/2005210/header.jpg?t=1666360949",
  "initialprice": "399",
  "languages": "English, Simplified Chinese, French, Japanese, Portuguese - Brazil, German, Traditional Chinese, Spanish - Spain, Korean",
  "name": "Void Scrappers",
  "negative": 15,
  "owners": "20,000 .. 50,000",
  "platforms": {
    "linux": true,
    "mac": true,
    "windows": true
  },
  "positive": 187,
  "price": "399",
  "publisher": "8BitSkull",
  "release_date": "2022/10/21",
  "required_age": 0,
  "tags": {
    "2D": 28,
    "Action": 120,
    "Action Roguelike": 138,
    "Aliens": 71,
    "Bullet Hell": 132,
    "Controller": 54,
    "Loot": 107,
    "Pixel Graphics": 69,
    "Retro": 39,
    "Rogue-like": 111,
    "Rogue-lite": 114,
    "Sci-fi": 82,
    "Score Attack": 101,
    "Shoot 'Em Up": 128,
    "Shooter": 95,
    "Singleplayer": 29,
    "Space": 91,
    "Top-Down Shooter": 124
  },
  "type": "game"
}