{
  "Average Playtime - 2 Weeks": 208,
  "Average Playtime - Forever": 1853,
  "CCU Histogram": {
    "2022-12-08": 2097,
    "2022-12-09": 1949,
    "2022-12-10": 2304,
    "2022-12-11": 2109,
    "2022-12-12": 1915,
    "2022-12-13": 1721,
    "2022-12-14": 1862,
    "2022-12-15": 2004,
    "2022-12-16": 2076,
    "2022-12-17": 2149,
    "2022-12-18": 2222,
    "2022-12-19": 2130,
    "2022-12-20": 2038,
    "2022-12-21": 1947,
    "2022-12-22": 2067
  },
  "Completion": 45.69999885559082,
  "Down 30 Days": 60,
  "Like Histogram": [
    {
      "date": 1667268000,
      "recommendations_down": 3,
      "recommendations_up": 18
    },
    {
      "date": 1667354400,
      "recommendations_down": 2,
      "recommendations_up": 22
    },
    {
      "date": 1667440800,
      "recommendations_down": 1,
      "recommendations_up": 17
    },
    {
      "date": 1667527200,
      "recommendations_down": 3,
      "recommendations_up": 28
    },
    {
      "date": 1667613600,
      "recommendations_down": 5,
      "recommendations_up": 35
    },
    {
      "date": 1667700000,
      "recommendations_down": 0,
      "recommendations_up": 20
    },
    {
      "date": 1667786400,
      "recommendations_down": 1,
      "recommendations_up": 18
    },
    {
      "date": 1667872800,
      "recommendations_down": 2,
      "recommendations_up": 13
    },
    {
      "date": 1667959200,
      "recommendations_down": 2,
      "recommendations_up": 19
    },
    {
      "date": 1668045600,
      "recommendations_down": 3,
      "recommendations_up": 23
    },
    {
      "date": 1668132000,
      "recommendations_down": 3,
      "recommendations_up": 30
    },
    {
      "date": 1668218400,
      "recommendations_down": 5,
      "recommendations_up": 31
    },
    {
      "date": 1668304800,
      "recommendations_down": 5,
      "recommendations_up": 32
    },
    {
      "date": 1668391200,
      "recommendations_down": 0,
      "recommendations_up": 22
    },
    {
      "date": 1668477600,
      "recommendations_down": 3,
      "recommendations_up": 30
    },
    {
      "date": 1668564000,
      "recommendations_down": 5,
      "recommendations_up": 22
    },
    {
      "date": 1668650400,
      "recommendations_down": 1,
      "recommendations_up": 26
    },
    {
      "date": 1668736800,
      "recommendations_down": 1,
      "recommendations_up": 40
    },
    {
      "date": 1668823200,
      "recommendations_down": 2,
      "recommendations_up": 32
    },
    {
      "date": 1668909600,
      "recommendations_down": 1,
      "recommendations_up": 29
    },
    {
      "date": 1668996000,
      "recommendations_down": 1,
      "recommendations_up": 19
    },
    {
      "date": 1669082400,
      "recommendations_down": 0,
      "recommendations_up": 33
    },
    {
      "date": 1669168800,
      "recommendations_down": 2,
      "recommendations_up": 29
    },
    {
      "date": 1669255200,
      "recommendations_down": 2,
      "recommendations_up": 42
    },
    {
      "date": 1669341600,
      "recommendations_down": 3,
      "recommendations_up": 42
    },
    {
      "date": 1669428000,
      "recommendations_down": 0,
      "recommendations_up": 39
    },
    {
      "date": 1669514400,
      "recommendations_down": 0,
      "recommendations_up": 38
    },
    {
      "date": 1669600800,
      "recommendations_down": 2,
      "recommendations_up": 10
    },
    {
      "date": 1669687200,
      "recommendations_down": 1,
      "recommendations_up": 16
    },
    {
      "date": 1669773600,
      "recommendations_down": 1,
      "recommendations_up": 3
    }
  ],
  "Median Playtime - 2 Weeks": 208,
  "Median Playtime - Forever": 805,
  "Meta Score": -1,
  "Rating": "?",
  "Up 30 Days": 778,
  "User Score": -1,
  "appid": 603850,
  "categories": [
    "Multi-player",
    "Single-player",
    "Steam Workshop",
    "Shared/Split Screen PvP",
    "Remote Play on Phone",
    "Remote Play on Tablet",
    "Remote Play Together",
    "PvP"
  ],
  "ccu": 1922,
  "consensus_genre": "Strategy",
  "developer": "\u0141ukasz Jakowski",
  "discount": "0",
  "genre": [
    "Strategy"
  ],
  "header_image": "https://cdn.akamai.steamstatic.com/steam/apps/603850/header.jpg?t=1666987848",
  "initialprice": "499",
  "languages": "English, German, Dutch, Russian, Greek, Polish, Romanian, Czech, Italian, Hungarian, French, Spanish - Spain, Turkish, Portuguese - Portugal, Korean, Traditional Chinese, Japanese, Portuguese - Brazil, Simplified Chinese",
  "name": "Age of History II",
  "negative": 3402,
  "owners": "1,000,000 .. 2,000,000",
  "platforms": {
    "linux": false,
    "mac": false,
    "windows": true
  },
  "positive": 24143,
  "price": "499",
  "publisher": "\u0141ukasz Jakowski Games",
  "release_date": "2018/11/21",
  "required_age": 0,
  "tags": {
    "Alternate History": 118,
    "Casual": 72,
    "Diplomacy": 145,
    "Grand Strategy": 327,
    "Historical": 375,
    "Indie": 107,
    "Multiplayer": 134,
    "Open World": 67,
    "Political": 160,
    "Political Sim": 196,
    "Politics": 134,
    "Sandbox": 170,
    "Simulation": 194,
    "Singleplayer": 168,
    "Strategy": 499,
    "Turn-Based": 202,
    "Turn-Based Strategy": 279,
    "War": 344,
    "World War I": 114,
    "World War II": 155
  },
  "type": "game"
}