{
  "appid": 39140,
  "name": "FINAL FANTASY VII",
  "developer": "Square Enix",
  "publisher": "Square Enix",
  "tags": {
    "JRPG": 1148,
    "RPG": 856,
    "Classic": 669,
    "Turn-Based": 524,
    "Story Rich": 501,
    "Singleplayer": 483,
    "Great Soundtrack": 470,
    "Fantasy": 380,
    "Retro": 200,
    "Adventure": 157,
    "Party-Based RPG": 135,
    "Epic": 133,
    "Open World": 130,
    "Sci-fi": 129,
    "Cyberpunk": 118,
    "Atmospheric": 115,
    "Exploration": 102,
    "Dystopian ": 98,
    "1990's": 85,
    "Strategy": 79
  },
  "type": "game",
  "categories": [
    "Single-player",
    "Partial Controller Support",
    "Steam Achievements",
    "Remote Play on Phone",
    "Remote Play on Tablet"
  ],
  "owners": "1,000,000 .. 2,000,000",
  "positive": 20754,
  "negative": 1565,
  "price": "1199",
  "initialprice": "1199",
  "discount": "0",
  "ccu": 365,
  "languages": "English, German, French, Spanish - Spain",
  "platforms": {
    "windows": true,
    "mac": false,
    "linux": false
  },
  "release_date": "2013/07/4",
  "required_age": "8",
  "header_image": "https://cdn.akamai.steamstatic.com/steam/apps/39140/header.jpg?t=1655449322",
  "genre": [
    "RPG"
  ],
  "consensus_genre": "RPG",
  "Meta Score": -1,
  "Like Histogram": [
    {
      "date": 1667268000,
      "recommendations_up": 1,
      "recommendations_down": 0
    }
  ],
  "Up 30 Days": 1,
  "Down 30 Days": 0,
  "Completion": -1,
  "Rating": "?"
}