{
  "appid": 1212750,
  "name": "Undead zombies",
  "developer": "\u4e4c\u62c9",
  "publisher": "\u4e4c\u62c9",
  "tags": {
    "Action": 32,
    "Indie": 31,
    "Adventure": 30,
    "Third Person": 13,
    "Violent": 11
  },
  "type": "game",
  "categories": [
    "Single-player"
  ],
  "owners": "0 .. 20,000",
  "positive": 0,
  "negative": 9,
  "price": "99",
  "initialprice": "99",
  "discount": "0",
  "ccu": 0,
  "languages": "English",
  "platforms": {
    "windows": true,
    "mac": false,
    "linux": false
  },
  "release_date": "2020/01/8",
  "required_age": 0,
  "header_image": "https://cdn.akamai.steamstatic.com/steam/apps/1212750/header.jpg?t=1578471616",
  "genre": [
    "Action",
    "Adventure",
    "Indie"
  ],
  "consensus_genre": "Action",
  "Meta Score": -1,
  "Like Histogram": [
    {
      "date": 1667268000,
      "recommendations_up": 1,
      "recommendations_down": 1
    },
    {
      "date": 1667354400,
      "recommendations_up": 0,
      "recommendations_down": 0
    },
    {
      "date": 1667440800,
      "recommendations_up": 0,
      "recommendations_down": 0
    }
  ],
  "Up 30 Days": 1,
  "Down 30 Days": 1,
  "Completion": [
    {
      "name": "Start_Game",
      "percent": 92.80000305175781
    },
    {
      "name": "Challenge_Lizard_Simple",
      "percent": 4.699999809265137
    },
    {
      "name": "Challenge_Hydra_Simple",
      "percent": 4.699999809265137
    },
    {
      "name": "Challenge_Beast_Simple",
      "percent": 4.699999809265137
    },
    {
      "name": "Challenge_Spider_Simple",
      "percent": 4.699999809265137
    },
    {
      "name": "Challenge_Vendigo_Hard",
      "percent": 2.299999952316284
    },
    {
      "name": "Challenge_Vendigo_Normal",
      "percent": 2.299999952316284
    },
    {
      "name": "Challenge_Vendigo_Simple",
      "percent": 2.299999952316284
    },
    {
      "name": "Challenge_Lizard_Hard",
      "percent": 2.299999952316284
    },
    {
      "name": "Challenge_Lizard_Normal",
      "percent": 2.299999952316284
    },
    {
      "name": "Challenge_Hydra_Hard",
      "percent": 2.299999952316284
    },
    {
      "name": "Challenge_Hydra_Normal",
      "percent": 2.299999952316284
    },
    {
      "name": "Challenge_Beast_Hard",
      "percent": 2.299999952316284
    },
    {
      "name": "Challenge_Beast_Normal",
      "percent": 2.299999952316284
    },
    {
      "name": "Challenge_Spider_Hard",
      "percent": 2.299999952316284
    },
    {
      "name": "Challenge_Spider_Normal",
      "percent": 2.299999952316284
    }
  ],
  "Rating": "?"
}