{
  "appid": 1390190,
  "name": "APICO",
  "developer": "TNgineers",
  "publisher": "Whitethorn Games",
  "tags": {
    "Exploration": 443,
    "Management": 439,
    "Education": 433,
    "Sandbox": 431,
    "Immersive Sim": 427,
    "Nature": 420,
    "Building": 415,
    "2D": 409,
    "Cute": 406,
    "Open World": 404,
    "Top-Down": 397,
    "Relaxing": 394,
    "Casual": 389,
    "Simulation": 377,
    "Indie": 287,
    "Pixel Graphics": 287,
    "Colorful": 280,
    "Online Co-Op": 277,
    "Singleplayer": 277,
    "Family Friendly": 267
  },
  "type": "game",
  "categories": [
    "Multi-player",
    "Single-player",
    "Co-op",
    "Partial Controller Support",
    "Steam Achievements",
    "Steam Cloud",
    "Cross-Platform Multiplayer",
    "Online Co-op"
  ],
  "owners": "50,000 .. 100,000",
  "positive": 502,
  "negative": 39,
  "price": "1999",
  "initialprice": "1999",
  "discount": "0",
  "ccu": 15,
  "languages": "English, French, Italian, German, Japanese, Portuguese - Brazil, Spanish - Latin America",
  "platforms": {
    "windows": true,
    "mac": true,
    "linux": true
  },
  "release_date": "2022/05/20",
  "required_age": 0,
  "header_image": "https://cdn.akamai.steamstatic.com/steam/apps/1390190/header.jpg?t=1659024343",
  "genre": [
    "Indie",
    "Simulation"
  ],
  "consensus_genre": "Simulation",
  "Meta Score": -1,
  "Like Histogram": [
    {
      "date": 1667268000,
      "recommendations_up": 0,
      "recommendations_down": 0
    },
    {
      "date": 1667354400,
      "recommendations_up": 0,
      "recommendations_down": 0
    },
    {
      "date": 1667440800,
      "recommendations_up": 0,
      "recommendations_down": 0
    },
    {
      "date": 1667527200,
      "recommendations_up": 0,
      "recommendations_down": 0
    },
    {
      "date": 1667613600,
      "recommendations_up": 0,
      "recommendations_down": 0
    },
    {
      "date": 1667700000,
      "recommendations_up": 0,
      "recommendations_down": 0
    },
    {
      "date": 1667786400,
      "recommendations_up": 0,
      "recommendations_down": 0
    },
    {
      "date": 1667872800,
      "recommendations_up": 0,
      "recommendations_down": 0
    },
    {
      "date": 1667959200,
      "recommendations_up": 0,
      "recommendations_down": 0
    },
    {
      "date": 1668045600,
      "recommendations_up": 0,
      "recommendations_down": 0
    },
    {
      "date": 1668132000,
      "recommendations_up": 0,
      "recommendations_down": 0
    },
    {
      "date": 1668218400,
      "recommendations_up": 0,
      "recommendations_down": 0
    },
    {
      "date": 1668304800,
      "recommendations_up": 0,
      "recommendations_down": 0
    },
    {
      "date": 1668391200,
      "recommendations_up": 0,
      "recommendations_down": 0
    }
  ],
  "Up 30 Days": 0,
  "Down 30 Days": 0,
  "Completion": -1,
  "Rating": "?"
}