{
  "Average Playtime - 2 Weeks": 0,
  "Average Playtime - Forever": 25,
  "CCU Histogram": {
    "2022-12-08": 38,
    "2022-12-09": 15,
    "2022-12-10": 61,
    "2022-12-11": 47,
    "2022-12-12": 34,
    "2022-12-13": 21,
    "2022-12-14": 27,
    "2022-12-15": 34,
    "2022-12-16": 36,
    "2022-12-17": 38,
    "2022-12-18": 41,
    "2022-12-19": 39,
    "2022-12-20": 38,
    "2022-12-21": 37,
    "2022-12-22": 25
  },
  "Completion": -1,
  "Down 30 Days": 116,
  "Like Histogram": [
    {
      "date": 1667268000,
      "recommendations_down": 0,
      "recommendations_up": 0
    },
    {
      "date": 1667354400,
      "recommendations_down": 2,
      "recommendations_up": 0
    },
    {
      "date": 1667440800,
      "recommendations_down": 0,
      "recommendations_up": 3
    },
    {
      "date": 1667527200,
      "recommendations_down": 0,
      "recommendations_up": 2
    },
    {
      "date": 1667613600,
      "recommendations_down": 1,
      "recommendations_up": 2
    },
    {
      "date": 1667700000,
      "recommendations_down": 2,
      "recommendations_up": 3
    },
    {
      "date": 1667786400,
      "recommendations_down": 1,
      "recommendations_up": 3
    },
    {
      "date": 1667872800,
      "recommendations_down": 1,
      "recommendations_up": 0
    },
    {
      "date": 1667959200,
      "recommendations_down": 0,
      "recommendations_up": 1
    },
    {
      "date": 1668045600,
      "recommendations_down": 1,
      "recommendations_up": 1
    },
    {
      "date": 1668132000,
      "recommendations_down": 0,
      "recommendations_up": 0
    },
    {
      "date": 1668218400,
      "recommendations_down": 0,
      "recommendations_up": 2
    },
    {
      "date": 1668304800,
      "recommendations_down": 3,
      "recommendations_up": 4
    },
    {
      "date": 1668391200,
      "recommendations_down": 2,
      "recommendations_up": 4
    },
    {
      "date": 1668477600,
      "recommendations_down": 21,
      "recommendations_up": 13
    },
    {
      "date": 1668564000,
      "recommendations_down": 20,
      "recommendations_up": 4
    },
    {
      "date": 1668650400,
      "recommendations_down": 10,
      "recommendations_up": 4
    },
    {
      "date": 1668736800,
      "recommendations_down": 10,
      "recommendations_up": 5
    },
    {
      "date": 1668823200,
      "recommendations_down": 8,
      "recommendations_up": 8
    },
    {
      "date": 1668909600,
      "recommendations_down": 5,
      "recommendations_up": 7
    },
    {
      "date": 1668996000,
      "recommendations_down": 3,
      "recommendations_up": 3
    },
    {
      "date": 1669082400,
      "recommendations_down": 4,
      "recommendations_up": 1
    },
    {
      "date": 1669168800,
      "recommendations_down": 11,
      "recommendations_up": 6
    },
    {
      "date": 1669255200,
      "recommendations_down": 2,
      "recommendations_up": 3
    },
    {
      "date": 1669341600,
      "recommendations_down": 1,
      "recommendations_up": 1
    },
    {
      "date": 1669428000,
      "recommendations_down": 1,
      "recommendations_up": 1
    },
    {
      "date": 1669514400,
      "recommendations_down": 2,
      "recommendations_up": 1
    },
    {
      "date": 1669600800,
      "recommendations_down": 1,
      "recommendations_up": 1
    },
    {
      "date": 1669687200,
      "recommendations_down": 2,
      "recommendations_up": 0
    },
    {
      "date": 1669773600,
      "recommendations_down": 2,
      "recommendations_up": 1
    }
  ],
  "Median Playtime - 2 Weeks": 0,
  "Median Playtime - Forever": 25,
  "Meta Score": -1,
  "Rating": "?",
  "Up 30 Days": 84,
  "User Score": -1,
  "appid": 2111630,
  "categories": [
    "Single-player"
  ],
  "ccu": 29,
  "consensus_genre": "Simulation",
  "developer": "ONGAKUKAN Co.,Ltd.",
  "discount": "0",
  "genre": [
    "Simulation",
    "Early Access"
  ],
  "header_image": "https://cdn.akamai.steamstatic.com/steam/apps/2111630/header.jpg?t=1664787504",
  "initialprice": "999",
  "languages": "English, Japanese",
  "name": "JR EAST Train Simulator",
  "negative": 93,
  "owners": "0 .. 20,000",
  "platforms": {
    "linux": false,
    "mac": false,
    "windows": true
  },
  "positive": 256,
  "price": "999",
  "publisher": "East Japan Railway Company",
  "release_date": "2022/09/19",
  "required_age": 0,
  "tags": {
    "2D Platformer": 38,
    "Automobile Sim": 32,
    "Driving": 44,
    "Early Access": 28,
    "FMV": 5,
    "Mechs": 26,
    "Realistic": 28,
    "Simulation": 55,
    "Singleplayer": 25,
    "Trains": 49,
    "Transportation": 42
  },
  "type": "game"
}