{
  "appid": 964440,
  "name": "Hell is Others",
  "developer": "Strelka Games, Yonder",
  "publisher": "A List Games",
  "tags": {
    "Multiplayer": 2711,
    "Difficult": 2654,
    "Perma Death": 2566,
    "Shoot 'Em Up": 2564,
    "Survival Horror": 2560,
    "Shooter": 2542,
    "Top-Down": 2533,
    "Gun Customization": 2498,
    "Fast-Paced": 2426,
    "Twin Stick Shooter": 2405,
    "Story Rich": 2379,
    "Replay Value": 2377,
    "Rogue-lite": 2364,
    "PvE": 2352,
    "Loot": 2331,
    "Philosophical": 2309,
    "Stealth": 2295,
    "Thriller": 2291,
    "Dark": 2261,
    "Dystopian ": 2149
  },
  "type": "game",
  "categories": [
    "Multi-player",
    "Partial Controller Support",
    "Steam Achievements",
    "Online PvP",
    "PvP"
  ],
  "owners": "200,000 .. 500,000",
  "positive": 510,
  "negative": 195,
  "price": "1499",
  "initialprice": "1499",
  "discount": "0",
  "ccu": 176,
  "languages": "English, French, Italian, German, Spanish - Spain, Korean, Portuguese - Brazil, Russian, Simplified Chinese, Traditional Chinese",
  "platforms": {
    "windows": true,
    "mac": false,
    "linux": false
  },
  "release_date": "2022/10/20",
  "required_age": 0,
  "header_image": "https://cdn.akamai.steamstatic.com/steam/apps/964440/header.jpg?t=1667917760",
  "genre": [
    "Action",
    "Adventure",
    "Indie"
  ],
  "consensus_genre": "",
  "Meta Score": -1,
  "Like Histogram": [
    {
      "date": 1667268000,
      "recommendations_up": 15,
      "recommendations_down": 13
    },
    {
      "date": 1667354400,
      "recommendations_up": 18,
      "recommendations_down": 8
    },
    {
      "date": 1667440800,
      "recommendations_up": 10,
      "recommendations_down": 9
    },
    {
      "date": 1667527200,
      "recommendations_up": 9,
      "recommendations_down": 9
    },
    {
      "date": 1667613600,
      "recommendations_up": 16,
      "recommendations_down": 8
    },
    {
      "date": 1667700000,
      "recommendations_up": 7,
      "recommendations_down": 8
    },
    {
      "date": 1667786400,
      "recommendations_up": 7,
      "recommendations_down": 9
    },
    {
      "date": 1667872800,
      "recommendations_up": 7,
      "recommendations_down": 5
    },
    {
      "date": 1667959200,
      "recommendations_up": 9,
      "recommendations_down": 5
    },
    {
      "date": 1668045600,
      "recommendations_up": 7,
      "recommendations_down": 2
    },
    {
      "date": 1668132000,
      "recommendations_up": 4,
      "recommendations_down": 3
    },
    {
      "date": 1668218400,
      "recommendations_up": 3,
      "recommendations_down": 2
    },
    {
      "date": 1668304800,
      "recommendations_up": 4,
      "recommendations_down": 2
    },
    {
      "date": 1668391200,
      "recommendations_up": 2,
      "recommendations_down": 2
    },
    {
      "date": 1668477600,
      "recommendations_up": 2,
      "recommendations_down": 5
    },
    {
      "date": 1668564000,
      "recommendations_up": 1,
      "recommendations_down": 4
    },
    {
      "date": 1668650400,
      "recommendations_up": 2,
      "recommendations_down": 4
    },
    {
      "date": 1668736800,
      "recommendations_up": 3,
      "recommendations_down": 3
    },
    {
      "date": 1668823200,
      "recommendations_up": 1,
      "recommendations_down": 0
    },
    {
      "date": 1668909600,
      "recommendations_up": 1,
      "recommendations_down": 2
    },
    {
      "date": 1668996000,
      "recommendations_up": 1,
      "recommendations_down": 2
    },
    {
      "date": 1669082400,
      "recommendations_up": 4,
      "recommendations_down": 2
    },
    {
      "date": 1669168800,
      "recommendations_up": 7,
      "recommendations_down": 2
    },
    {
      "date": 1669255200,
      "recommendations_up": 19,
      "recommendations_down": 2
    },
    {
      "date": 1669341600,
      "recommendations_up": 9,
      "recommendations_down": 1
    },
    {
      "date": 1669428000,
      "recommendations_up": 4,
      "recommendations_down": 1
    },
    {
      "date": 1669514400,
      "recommendations_up": 2,
      "recommendations_down": 1
    },
    {
      "date": 1669600800,
      "recommendations_up": 1,
      "recommendations_down": 1
    },
    {
      "date": 1669687200,
      "recommendations_up": 2,
      "recommendations_down": 0
    },
    {
      "date": 1669773600,
      "recommendations_up": 3,
      "recommendations_down": 2
    }
  ],
  "Up 30 Days": 180,
  "Down 30 Days": 117,
  "Completion": 29.299999237060547,
  "Rating": "?"
}